<?xml version="1.0" encoding="UTF-8"?>
<service name="reportService" scope="request">
    <description>
        report Service
    </description>
    <operation name="getRScriptlets">
        <messageReceiver class="org.apache.axis2.receivers.RawXMLINOutMessageReceiver"/>
    </operation>
    <operation name="getRResults">
        <messageReceiver class="org.apache.axis2.receivers.RawXMLINOutMessageReceiver"/>
    </operation>
    <parameter name="ServiceClass">de.hpi.i2b2.report.reportService</parameter>
</service>
